HaplyHardwareAPI.cpython-312-i386-linux-gnu.so
HaplyHardwareAPI-0.1.12.dist-info/RECORD
HaplyHardwareAPI-0.1.12.dist-info/WHEEL
HaplyHardwareAPI-0.1.12.dist-info/METADATA
HaplyHardwareAPI-0.1.12.dist-info/top_level.txt
