Metadata-Version: 2.1
Name: HaplyHardwareAPI
Version: 0.1.12
Summary: Python API for Haply Hardware
Author: Haply Robotics
Author-email: antoine@haply.co
Requires-Python: >=3.7
Provides-Extra: test
Requires-Dist: pytest >=6.0 ; extra == 'test'
